{
  "candidate_id": "c-51fa9674e6303cc1",
  "experiment_name": "optical_intervention_electrical",
  "provider": "stage",
  "scenario": "matched_transport",
  "evidence_level": "measured",
  "config_id": "S-Native",
  "config_hash": "a21641b69e085bb1afc147209ca703de820afe279a5870193dfcc325b14274bd",
  "axes": {
    "repeat": 1
  },
  "resolved": {
    "schema_version": "aspg-candidate-config-1.0",
    "base_config": {
      "schema_version": "aspg-final-config-1.0",
      "config_id": "S-Native",
      "purpose": "STAGE-native heterogeneous system for bottleneck migration and co-design",
      "evidence_level": "measured",
      "compute": {
        "processing_elements": 16,
        "macs_per_pe_per_cycle": 256,
        "aggregate_macs_per_cycle": 4096
      },
      "transport": {
        "topology": "mesh_4x4",
        "router_count": 16,
        "endpoint_count": 16,
        "link_bits_per_cycle": 128,
        "packet_bits": 128
      },
      "memory": {
        "ports": 1,
        "latency_cycles": 5
      },
      "special_units": {
        "reduction_latency_cycles": 2,
        "softmax_latency_cycles": 8
      },
      "queue_capacity_packets": 4,
      "workloads": {
        "primary": "Attention_128_64",
        "auxiliary": "GEMM_256"
      }
    },
    "parameters": {
      "transport_mode": "electrical_contended",
      "channel_capacity": 1,
      "queue_depth": 4,
      "payload_bits": 128,
      "flow_count": 8,
      "graph_hash": "bf10f69d94b3ad849c1317ccb75ca98e01f67de0ed54b3d19411f1ac344ecdf0",
      "mapping_hash": "385d4a3ce97fce9d99930055b3a9f005d8af2623eeb227d53bbbabb476595597",
      "compute_hash": "289070eea5adcc3f7f275c07a9285ea55d089995358fc53159da644b3c87437e",
      "memory_hash": "515cce82b207b8cfd8f34d4d6e93fd49feb4ba890d579bfb0e61603c05450c2d",
      "endpoint_hash": "043bd74e95652e3021b7cb36e62a6c4c645f0155a003ccd8a148f96ea4908df1",
      "transport_hash": "a36f895358971c81cf6ab9b7471fd66d3845e67a17a94e3692986ee736b3ed5a",
      "case_id": "attention_128_64",
      "packet_count": 8192,
      "workload_hash": "fbe0d419e11d7eec23c613659c5bb85a287de71e1ecb8e63b58488287edd5272",
      "repeat": 1
    }
  }
}
